UcsSdk
