Metadata-Version: 1.0
Name: UcsSdk
Version: 0.8.2.5
Summary: Python SDK for Cisco UCS Manager
Home-page: UNKNOWN
Author: Cisco Systems
Author-email: UNKNOWN
License: LICENSE.txt
Platform: UNKNOWN
